kenpompy/FanMatch.py
kenpompy/_DESAdapter.py
kenpompy/__init__.py
kenpompy/conference.py
kenpompy/misc.py
kenpompy/summary.py
kenpompy/team.py
kenpompy/utils.py
kenpompy-0.4.0.dist-info/LICENSE
kenpompy-0.4.0.dist-info/METADATA
kenpompy-0.4.0.dist-info/WHEEL
kenpompy-0.4.0.dist-info/top_level.txt
kenpompy-0.4.0.dist-info/RECORD
