Metadata-Version: 2.1
Name: kenpompy
Version: 0.4.0
Summary: A python package for scraping kenpom.com NCAA basketball data.
Home-page: https://github.com/j-andrews7/kenpompy
Author: Jared Andrews
Author-email: jared.andrews07@gmail.com
License: GNU GPLv3
Classifier: Programming Language :: Python :: 3
Classifier: License :: OSI Approved :: GNU General Public License v3 (GPLv3)
Classifier: Operating System :: OS Independent
Classifier: Development Status :: 4 - Beta
Classifier: Intended Audience :: Science/Research
Classifier: Intended Audience :: Developers
Requires-Python: >=3.8
License-File: LICENSE
Requires-Dist: mechanicalsoup
Requires-Dist: pandas
Requires-Dist: bs4
Requires-Dist: cloudscraper
